_pytamer.cpython-311-darwin.so
pytamer.py
pytamer-0.1.22.dist-info/METADATA
pytamer-0.1.22.dist-info/WHEEL
pytamer-0.1.22.dist-info/top_level.txt
pytamer-0.1.22.dist-info/RECORD
