Metadata-Version: 2.4
Name: pytamer
Version: 0.1.22
Summary: TAMER API
Home-page: https://tamer.fbk.eu
Author: FBK Tamer Development Team
Author-email: tamer@fbk.eu
License: Free For Educational Use
Dynamic: author
Dynamic: author-email
Dynamic: home-page
Dynamic: license
Dynamic: summary
